welp/__init__.py
welp/__main__.py
welp/business_data.py
welp/click_data.py
welp/menus.py
welp/welp.py
welp/api/__init__.py
welp/api/client.py
welp/api/geolocation.py
welp/api/yelp.py
welp/api/google/__init__.py
welp/api/google/geolocation.py
welp/api/yelp/__init__.py
welp/api/yelp/business.py
welp/api/yelp/yelp.py
whateat/__init__.py
whateat/__main__.py
whateat/api/__init__.py
whateat/api/geolocation.py
whateat/api/yelp.py
welp-0.0.5.dist-info/LICENSE
welp-0.0.5.dist-info/METADATA
welp-0.0.5.dist-info/WHEEL
welp-0.0.5.dist-info/entry_points.txt
welp-0.0.5.dist-info/top_level.txt
welp-0.0.5.dist-info/RECORD
