Metadata-Version: 2.1
Name: welp
Version: 0.0.5
Summary: what should i eat?
Home-page: https://github.com/azye/welp
Author: Alex Ye
Author-email: alexzye1@gmail.com
License: UNKNOWN
Platform: UNKNOWN
Requires-Python: >=3.6
Requires-Dist: click
Requires-Dist: geocoder
